Ogre/Bites.py
Ogre/Bullet.py
Ogre/HighPy.py
Ogre/ImGui.py
Ogre/Numpy.py
Ogre/Ogre.py
Ogre/Overlay.py
Ogre/RTShader.py
Ogre/Terrain.py
Ogre/_Bites.so
Ogre/_Bullet.so
Ogre/_ImGui.so
Ogre/_Ogre.so
Ogre/_Overlay.so
Ogre/_RTShader.so
Ogre/_Terrain.so
Ogre/__init__.py
Ogre/libOgreBites.14.5.dylib
Ogre/libOgreBites.dylib
Ogre/libOgreBullet.dylib
Ogre/libOgreMain.14.5.dylib
Ogre/libOgreMain.dylib
Ogre/libOgreOverlay.14.5.dylib
Ogre/libOgreOverlay.dylib
Ogre/libOgrePaging.14.5.dylib
Ogre/libOgrePaging.dylib
Ogre/libOgreRTShaderSystem.14.5.dylib
Ogre/libOgreRTShaderSystem.dylib
Ogre/libOgreTerrain.14.5.dylib
Ogre/libOgreTerrain.dylib
Ogre/libSDL2-2.0.0.dylib
Ogre/libSDL2-2.0.dylib
Ogre/libSDL2.dylib
Ogre/libz.1.3.1.dylib
Ogre/libz.1.dylib
Ogre/libz.dylib
Ogre/OGRE/Codec_Assimp.14.5.dylib
Ogre/OGRE/Codec_Assimp.dylib
Ogre/OGRE/Codec_STBI.14.5.dylib
Ogre/OGRE/Codec_STBI.dylib
Ogre/OGRE/Plugin_DotScene.14.5.dylib
Ogre/OGRE/Plugin_DotScene.dylib
Ogre/OGRE/Plugin_OctreeSceneManager.14.5.dylib
Ogre/OGRE/Plugin_OctreeSceneManager.dylib
Ogre/OGRE/Plugin_ParticleFX.14.5.dylib
Ogre/OGRE/Plugin_ParticleFX.dylib
Ogre/OGRE/RenderSystem_GL.14.5.dylib
Ogre/OGRE/RenderSystem_GL.dylib
Ogre/OGRE/RenderSystem_GL3Plus.14.5.dylib
Ogre/OGRE/RenderSystem_GL3Plus.dylib
Ogre/OGRE/RenderSystem_Tiny.14.5.dylib
Ogre/OGRE/RenderSystem_Tiny.dylib
ogre_python-14.5.2.data/data/Media/Main/DefaultShaders.metal
ogre_python-14.5.2.data/data/Media/Main/GLSL_GL3Support.glsl
ogre_python-14.5.2.data/data/Media/Main/HLSL_SM4Support.hlsl
ogre_python-14.5.2.data/data/Media/Main/OgreUnifiedShader.h
ogre_python-14.5.2.data/data/Media/Main/Shadow.material
ogre_python-14.5.2.data/data/Media/Main/ShadowBlend.frag
ogre_python-14.5.2.data/data/Media/Main/ShadowBlend.vert
ogre_python-14.5.2.data/data/Media/Main/ShadowExtrudeDirLight.vert
ogre_python-14.5.2.data/data/Media/Main/ShadowExtrudeDirLightFinite.vert
ogre_python-14.5.2.data/data/Media/Main/ShadowExtrudePointLight.vert
ogre_python-14.5.2.dist-info/licenses/AUTHORS
ogre_python-14.5.2.dist-info/licenses/LICENSE
ogre_python-14.5.2.dist-info/METADATA
ogre_python-14.5.2.dist-info/WHEEL
ogre_python-14.5.2.dist-info/top_level.txt
ogre_python-14.5.2.dist-info/RECORD
