Metadata-Version: 2.4
Name: ogre-python
Version: 14.5.2
Summary: Object-Oriented Graphics Rendering Engine - python package
Home-page: https://www.ogre3d.org
Maintainer: Pavel Rojtberg
License: MIT
Project-URL: Documentation, https://ogrecave.github.io/ogre/api/latest/manual.html
Project-URL: Source code, https://github.com/OGRECave/ogre
Project-URL: Issues, https://github.com/OGRECave/ogre/issues
Project-URL: Funding, https://www.patreon.com/ogre1
Classifier: Development Status :: 5 - Production/Stable
Classifier: Environment :: Console
Classifier: Intended Audience :: Developers
Classifier: Intended Audience :: Education
Classifier: Intended Audience :: Information Technology
Classifier: Intended Audience :: Science/Research
Classifier: License :: OSI Approved :: MIT License
Classifier: Operating System :: MacOS
Classifier: Operating System :: Microsoft :: Windows
Classifier: Operating System :: POSIX
Classifier: Operating System :: Unix
Classifier: Programming Language :: Python
Classifier: Programming Language :: Python :: 3
Classifier: Programming Language :: Python :: 3 :: Only
Classifier: Programming Language :: Python :: 3.8
Classifier: Programming Language :: C++
Classifier: Programming Language :: Python :: Implementation :: CPython
Classifier: Topic :: Scientific/Engineering
Classifier: Topic :: Multimedia :: Graphics :: 3D Rendering
Classifier: Topic :: Software Development
Requires-Python: >=3.6
License-File: LICENSE
License-File: AUTHORS
Dynamic: classifier
Dynamic: description
Dynamic: description-content-type
Dynamic: home-page
Dynamic: license
Dynamic: license-file
Dynamic: maintainer
Dynamic: project-url
Dynamic: requires-python
Dynamic: summary
